{
  "auth": "github:scriptkitties",
  "authors": [
    "Patrick Spek <p.spek@tyil.work>"
  ],
  "depends": [
    "Config",
    "Config::Parser::toml",
    "IO::Path::XDG",
    "IRC::Client",
    "IRC::Client::Plugin::NickServ:ver<0.3.0+>:api<0>",
    "IRC::Client::Plugin::DiceRolls",
    "Log",
    "Log::Colored"
  ],
  "description": "Raku based IRC bot for Scriptkitties",
  "license": "AGPL-3.0",
  "name": "Musashi",
  "perl": "6.d",
  "provides": {
    "Local::Musashi": "lib/Local/Musashi.pm6",
    "musashi": "bin/musashi.pl6"
  },
  "source-url": "https://gitlab.com/skitties/musashi",
  "tags": [
    "IRC"
  ],
  "version": "0.0.1"
}
